keyboard_api.py
keyboard_api-1.0.0.dist-info/WHEEL
keyboard_api-1.0.0.dist-info/METADATA
keyboard_api-1.0.0.dist-info/RECORD
